{
  "id": "anthias",
  "name": "Anthias",
  "description": "Open source digital signage software for Raspberry Pi and PCs.",
  "website": "https://anthias.screenly.io/",
  "headquarters": "USA",
  "open_source": true,
  "self_signup": false,
  "year_founded": 2022,
  "notes": [],
  "stats": {},
  "has_logo": true,
  "categories": [
    "CMS"
  ],
  "models": [
    {
      "delivery": "cloud",
      "pricing": [],
      "free_trial": false,
      "pricing_available": false,
      "has_freemium": false
    }
  ],
  "cms_properties": {
    "supported_platforms": [
      "Linux",
      "Raspberry Pi"
    ]
  },
  "discontinued": false
}