{
  "id": "neon",
  "name": "Neon",
  "description": "",
  "website": "https://www.neonscreens.com/digital-signage",
  "headquarters": "USA",
  "open_source": false,
  "self_signup": false,
  "year_founded": 2021,
  "notes": [],
  "stats": {},
  "has_logo": true,
  "categories": [
    "CMS"
  ],
  "models": [
    {
      "delivery": "cloud",
      "pricing": [
        {
          "name": "Digital Signage",
          "payment_model": "subscription",
          "billing_basis": "per_device",
          "monthly": 35,
          "yearly": 360
        }
      ],
      "free_trial": true,
      "pricing_available": true,
      "has_freemium": false
    }
  ],
  "cms_properties": {
    "supported_platforms": [
      "Android",
      "Fire OS",
      "Tizen",
      "webOS"
    ]
  },
  "discontinued": false
}