{
  "id": "studiopro",
  "name": "StudioPro",
  "description": "",
  "website": "https://www.videoteldigital.com/pages/studioweb-and-studiopro-cloud-based-software-subscription-based",
  "headquarters": "USA",
  "open_source": false,
  "self_signup": false,
  "year_founded": 2022,
  "notes": [],
  "stats": {},
  "has_logo": true,
  "categories": [
    "CMS"
  ],
  "models": [
    {
      "delivery": "cloud",
      "pricing": [
        {
          "name": "Per screen",
          "payment_model": "subscription",
          "billing_basis": "per_device",
          "monthly": 10,
          "yearly": null
        }
      ],
      "free_trial": false,
      "pricing_available": true,
      "has_freemium": false
    }
  ],
  "cms_properties": {
    "supported_platforms": [
      "Windows",
      "macOS"
    ]
  },
  "discontinued": false
}